MANIFEST.in
README.md
setup.py
csp/__init__.py
csp/defer.py
csp/impl/__init__.py
csp/impl/buffers.py
csp/impl/channels.py
csp/impl/dispatch.py
csp/impl/interfaces.py
csp/impl/operations.py
csp/impl/process.py
csp/impl/select.py
csp/impl/timers.py
csp/test/__init__.py
csp/test/operations.py
csp/test/test_basic_callback_api.py
csp/test/test_basic_deferred_api.py
csp/test/test_buffers.py
example/__init__.py
example/blocking.py
example/buffered.py
example/closed.py
example/go_block.py
example/http.py
example/mapping.py
example/select.py
example/go/__init__.py
example/go/boring.py
example/go/boring_multiplexing.py
example/go/boring_service.py
example/go/daisy_chain.py
example/go/fan_in_select.py
example/go/pingpong.py
example/go/restoring_sequencing.py
example/go/timeout_for_whole_conversation_using_select.py
example/go/timeout_using_select.py
twisted_csp.egg-info/PKG-INFO
twisted_csp.egg-info/SOURCES.txt
twisted_csp.egg-info/dependency_links.txt
twisted_csp.egg-info/requires.txt
twisted_csp.egg-info/top_level.txt