Metadata-Version: 1.0
Name: twisted-csp
Version: 0.2.0
Summary: Go-style channels for Twisted
Home-page: https://github.com/ubolonton/twisted-csp
Author: Nguyễn Tuấn Anh
Author-email: ubolonton@gmail.com
License: EPL
Platform: UNKNOWN
